argame/__init__.py
argame/argame.py
GrowUp_Tech_Solutionss-2.0.2.dist-info/LICENSE
GrowUp_Tech_Solutionss-2.0.2.dist-info/METADATA
GrowUp_Tech_Solutionss-2.0.2.dist-info/WHEEL
GrowUp_Tech_Solutionss-2.0.2.dist-info/top_level.txt
GrowUp_Tech_Solutionss-2.0.2.dist-info/RECORD
