Metadata-Version: 2.1
Name: GrowUp-Tech-Solutionss
Version: 2.0.2
Summary: PythonTutorial
Author: Shahmir Khan
Author-email: DevShahmirKhan@gmail.com
Keywords: Guesture,Game,Controller of figs,area,developergautam
Classifier: Development Status :: 1 - Planning
Classifier: Intended Audience :: Developers
Classifier: Programming Language :: Python :: 3
Classifier: Operating System :: Unix
Classifier: Operating System :: MacOS :: MacOS X
Classifier: Operating System :: Microsoft :: Windows
License-File: LICENSE
